{
    "/home/js/bootstrap.js": "/home/js/bootstrap.js",
    "/admin/js/script.js": "/admin/js/script.js",
    "/js/app.js": "/js/app.js",
    "/css/app.css": "/css/app.css",
    "/home/js/raphael-min.js": "/home/js/raphael-min.js",
    "/home/css/font-awesome.css": "/home/css/font-awesome.css",
    "/home/js/jquery.js": "/home/js/jquery.js",
    "/home/css/custom/style.css": "/home/css/custom/style.css",
    "/home/css/responsive.css": "/home/css/responsive.css",
    "/home/js/tether.min.js": "/home/js/tether.min.js",
    "/home/js/custom.js": "/home/js/custom.js",
    "/home/css/colors.css": "/home/css/colors.css",
    "/home/css/bootstrap.css": "/home/css/bootstrap.css",
    "/home/images/ads-bg.png": "/home/images/ads-bg.png",
    "/home/images/apple-touch-icon.png": "/home/images/apple-touch-icon.png",
    "/home/images/arrow.png": "/home/images/arrow.png",
    "/home/images/favicon.ico": "/home/images/favicon.ico",
    "/home/images/flogo.png": "/home/images/flogo.png",
    "/home/images/footer.png": "/home/images/footer.png",
    "/home/images/hover.png": "/home/images/hover.png",
    "/home/images/loader.gif": "/home/images/loader.gif",
    "/home/images/logo.png": "/home/images/logo.png",
    "/home/images/menubg.jpg": "/home/images/menubg.jpg",
    "/home/images/videohover.png": "/home/images/videohover.png",
    "/home/fonts/FontAwesome.otf": "/home/fonts/FontAwesome.otf",
    "/home/fonts/fontawesome-webfont.eot": "/home/fonts/fontawesome-webfont.eot",
    "/home/fonts/fontawesome-webfont.svg": "/home/fonts/fontawesome-webfont.svg",
    "/home/fonts/fontawesome-webfont.ttf": "/home/fonts/fontawesome-webfont.ttf",
    "/home/fonts/fontawesome-webfont.woff": "/home/fonts/fontawesome-webfont.woff",
    "/home/fonts/fontawesome-webfont.woff2": "/home/fonts/fontawesome-webfont.woff2",
    "/admin/css/styles.css": "/admin/css/styles.css"
}
